{"name":"fdeffafbbf","url":"https://www.y03owzrr2dnub.com/home","showName":"抢单","appid":"com.fdeffafbbf.pakeplus","icon":"","iconPath":"","iconRound":true,"state":true,"single":true,"injectJq":true,"tauriApi":false,"devbug":false,"version":"0.0.3","preview":"Android","platform":["1-1","2-2"],"width":412,"height":915,"desc":"","jsFile":[],"filterCss":"","customJs":"(function(){\n    'use strict';\n\n    // ====================== 配置 ======================\n    const START_HOUR = 10;\n    const CLICK_END_MINUTE = 4;\n    const BTN_TEXT = '重新获取任务';\n    const FINISH_TEXT = '拉取完毕';\n\n    // ====================== 状态 ======================\n    let isWaiting = false;\n    let firstClick = true;\n    let taskStopped = false;\n    let refreshTriggered = false;\n    let blankTimer = null;\n\n    // ====================== 本地存储账号密码 ======================\n    const AuthStorage = {\n        KEY_USER: \"saved_username\",\n        KEY_PWD: \"saved_password\",\n        save(u, p) {\n            if (u && p) {\n                localStorage.setItem(this.KEY_USER, u);\n                localStorage.setItem(this.KEY_PWD, p);\n            }\n        },\n        load() {\n            return {\n                u: localStorage.getItem(this.KEY_USER) || \"\",\n                p: localStorage.getItem(this.KEY_PWD) || \"\"\n            };\n        }\n    };\n\n    // ====================== 超强自动填充（照搬你油猴的逻辑） ======================\n    function fillLoginInfo() {\n        const { u: USERNAME, p: PASSWORD } = AuthStorage.load();\n        if (!USERNAME || !PASSWORD) return;\n\n        const userInput = document.querySelector('input[placeholder=\"输入用户名称\"]');\n        const pwdInput = document.querySelector('input[placeholder=\"请输入密码\"]');\n\n        if (userInput && !userInput.value.trim()) {\n            userInput.value = USERNAME;\n            userInput.dispatchEvent(new Event('input', { bubbles: true }));\n            userInput.dispatchEvent(new Event('change', { bubbles: true }));\n        }\n\n        if (pwdInput && !pwdInput.value.trim()) {\n            pwdInput.value = PASSWORD;\n            pwdInput.dispatchEvent(new Event('input', { bubbles: true }));\n            pwdInput.dispatchEvent(new Event('change', { bubbles: true }));\n        }\n    }\n\n    // 监听输入，自动保存\n    function watchAndSave() {\n        const userInput = document.querySelector('input[placeholder=\"输入用户名称\"]');\n        const pwdInput = document.querySelector('input[placeholder=\"请输入密码\"]');\n        if (!userInput || !pwdInput) return;\n\n        function save() {\n            AuthStorage.save(userInput.value.trim(), pwdInput.value.trim());\n        }\n        userInput.addEventListener('input', save);\n        pwdInput.addEventListener('input', save);\n    }\n\n    // 持续监听页面变化，保证退出登录也能自动填（你油猴最关键的逻辑）\n    function startAutoFill() {\n        // 首次执行\n        fillLoginInfo();\n        watchAndSave();\n\n        // 监听DOM变化（退出登录、重新渲染都能触发）\n        const observer = new MutationObserver(fillLoginInfo);\n        observer.observe(document.body, {\n            childList: true,\n            subtree: true,\n            attributes: true\n        });\n\n        // 页面显示、焦点回来都填\n        window.addEventListener('pageshow', fillLoginInfo);\n        window.addEventListener('focus', fillLoginInfo);\n\n        // 100ms兜底，绝对不失效\n        setInterval(fillLoginInfo, 100);\n    }\n\n    // ====================== 抢任务逻辑（你原来的不变） ======================\n    function isWorkTime() {\n        return new Date().getHours() >= START_HOUR;\n    }\n\n    function is10ClickTime() {\n        const now = new Date();\n        return now.getHours() === 10 && now.getMinutes() >= 0 && now.getMinutes() <= CLICK_END_MINUTE;\n    }\n\n    function is11UpClickTime() {\n        const now = new Date();\n        return now.getHours() >= 11 && now.getMinutes() >= 0 && now.getMinutes() <= CLICK_END_MINUTE;\n    }\n\n    function isCodeError() {\n        const t = (document.body.innerText + document.title).toLowerCase();\n        const keys = ['502','503','504','500','404','网关超时','错误网关','服务不可用','服务器错误'];\n        return keys.some(k => t.includes(k));\n    }\n\n    function isBlank() {\n        const t = (document.body.innerText || '').trim().replace(/\\s+/g, '');\n        return t.length === 0;\n    }\n\n    function getBtn() {\n        return Array.from(document.querySelectorAll('*')).find(el =>\n            el.textContent?.trim() === BTN_TEXT && el.offsetParent\n        );\n    }\n\n    function runRefresh() {\n        if (!isWorkTime()) return;\n\n        if (isCodeError() && !refreshTriggered) {\n            refreshTriggered = true;\n            location.reload(true);\n            setTimeout(() => { refreshTriggered = false; }, 1000);\n            return;\n        }\n\n        if (isBlank() && !refreshTriggered && !blankTimer) {\n            refreshTriggered = true;\n            blankTimer = setTimeout(() => {\n                location.reload(true);\n                refreshTriggered = false;\n                blankTimer = null;\n            }, 5000);\n        }\n    }\n\n    function runTask() {\n        if (!isWorkTime()) return;\n\n        const now = new Date();\n        const m = now.getMinutes();\n        if (m === 0) {\n            taskStopped = false;\n            firstClick = true;\n        }\n\n        if (is10ClickTime()) {\n            if (taskStopped) return;\n            if (document.body.innerText.includes(FINISH_TEXT)) {\n                taskStopped = true;\n                return;\n            }\n        }\n\n        if (!is10ClickTime() && !is11UpClickTime()) return;\n        if (isWaiting) return;\n\n        const btn = getBtn();\n        if (!btn) return;\n\n        if (firstClick) {\n            try { btn.click(); } catch(e) {}\n            firstClick = false;\n            return;\n        }\n\n        isWaiting = true;\n        const delay = Math.random() * 2000;\n        setTimeout(() => {\n            try { getBtn()?.click(); } catch(e) {}\n            isWaiting = false;\n        }, delay);\n    }\n\n    // ====================== 启动 ======================\n    function start() {\n        startAutoFill();  // 这里就是你油猴那种超强自动填充\n        runTask();\n        runRefresh();\n        setInterval(() => { runTask(); runRefresh(); }, 300);\n    }\n\n    if (document.readyState === 'loading') {\n        document.addEventListener('DOMContentLoaded', start);\n    } else {\n        start();\n    }\n})();\n","isHtml":false,"htmlPath":"","htmlFiles":[],"prefix":"","pcRepo":"PakePlus-v2.1.8","iosRepo":"PakePlus-iOS-v2.1.8","androidRepo":"PakePlus-Android-v2.1.8","more":{"windows":{"label":"","title":"抢单","url":"https://www.y03owzrr2dnub.com/home","userAgent":"Mozilla/5.0 (Linux; Android 14; Pixel 6) AppleWebKit/537.36 (KHTML, like Gecko) Chrome/130.0.0.0 Mobile Safari/537.36","width":412,"height":915,"theme":null,"resizable":true,"fullscreen":false,"maximized":false,"minWidth":400,"minHeight":300,"maxWidth":1920,"maxHeight":1080,"decorations":true,"transparent":false,"titleBarStyle":"Visible","visible":true,"focus":true,"closable":true,"minimizable":true,"maximizable":true,"alwaysOnTop":false,"alwaysOnBottom":false,"center":false,"shadow":true,"skipTaskbar":false,"tabbingIdentifier":null,"parent":null,"dragDropEnabled":true,"browserExtensionsEnabled":false,"devtools":true,"contentProtected":false,"hiddenTitle":false,"incognito":false,"proxyUrl":null,"useHttpsScheme":false,"zoomHotkeysEnabled":false,"acceptFirstMouse":false,"create":false,"backgroundColor":null,"backgroundThrottling":null,"javascriptDisabled":false}},"phone":{"fullScreen":false,"safeArea":{"top":0,"bottom":0,"left":0,"right":0},"header":{"show":false,"title":"","backgroundColor":"","color":"","fontSize":16,"fontWeight":"bold","loading":false,"toolBar":false,"toolBarBackgroundColor":"","toolBarColor":"","toolBarFontSize":16,"toolBarFontWeight":"bold"},"siderMenu":{"show":false,"width":0,"backgroundColor":"","color":"","fontSize":16,"fontWeight":"bold","title":"","titleColor":"","titleFontSize":16,"titleFontWeight":"bold"},"tabBar":{"show":false,"backgroundColor":"","color":"","activeColor":"","fontSize":16,"fontWeight":"bold","tabBarItem":[]},"webview":{"userAgent":"","javaScriptEnabled":true,"domStorageEnabled":true,"allowFileAccess":true,"loadWithOverviewMode":true,"setSupportZoom":true,"clearCache":true}},"ios":{"name":"fdeffafbbf","showName":"抢单","version":"0.0.3","webUrl":"https://www.y03owzrr2dnub.com/home","id":"com.fdeffafbbf.pakeplus.ios","icon":"./app-icon.png","desc":"Package for personal use only, please do not use for commercial purposes（打包仅限个人使用，请勿传播或商业用途）","pubBody":"Package for personal use only, please do not use for commercial purposes（打包仅限个人使用，请勿传播或商业用途）","isHtml":false,"debug":false,"safeArea":"all"},"android":{"name":"fdeffafbbf","showName":"抢单","version":"0.0.3","webUrl":"https://www.y03owzrr2dnub.com/home","id":"com.fdeffafbbf.pakeplus.android","icon":"./app-icon.png","input":"./app-icon.png","output":"./res","rounded":true,"copyTo":"./app/src/main/res","androidResDir":"./app/src/main/res","desc":"Package for personal use only, please do not use for commercial purposes（打包仅限个人使用，请勿传播或商业用途）","pubBody":"Package for personal use only, please do not use for commercial purposes（打包仅限个人使用，请勿传播或商业用途）","isHtml":false,"debug":false,"safeArea":"all"},"desktop":{"name":"fdeffafbbf","showName":"抢单","version":"0.0.3","id":"com.fdeffafbbf.pakeplus.desktop","desc":"打包仅限个人使用，请勿传播或商业用途，否则后果自负","webUrl":"https://www.y03owzrr2dnub.com/home","iconPath":"../app-icon.png","inputPath":"../app-icon.png","tempPath":"./processed-image.png","icnsPath":"../src-tauri/icons/icon.icns","pubBody":"打包仅限个人使用，请勿传播或商业用途，否则后果自负","isHtml":false,"single":true,"state":true,"injectJq":false,"tauriApi":false,"buildMethod":"cloud","debug":false}}